markdown_inline_graphviz.py
markdown_inline_graphviz_extension-1.1.3.dist-info/licenses/LICENSE
markdown_inline_graphviz_extension-1.1.3.dist-info/METADATA
markdown_inline_graphviz_extension-1.1.3.dist-info/WHEEL
markdown_inline_graphviz_extension-1.1.3.dist-info/top_level.txt
markdown_inline_graphviz_extension-1.1.3.dist-info/RECORD
